traitschema/__init__.py
traitschema/io.py
traitschema/schema.py
traitschema-1.2.0.dist-info/DESCRIPTION.rst
traitschema-1.2.0.dist-info/METADATA
traitschema-1.2.0.dist-info/RECORD
traitschema-1.2.0.dist-info/WHEEL
traitschema-1.2.0.dist-info/metadata.json
traitschema-1.2.0.dist-info/top_level.txt
