Metadata-Version: 2.0
Name: traitschema
Version: 1.2.0
Summary: Serializable schema using traits
Home-page: https://github.com/mivade/traitschema
Author: Michael V. DePalatis
Author-email: mike@depalatis.net
License: BSD
Platform: UNKNOWN
Classifier: Development Status :: 5 - Production/Stable
Classifier: Intended Audience :: Developers
Classifier: Intended Audience :: Science/Research
Classifier: License :: OSI Approved :: BSD License
Classifier: Programming Language :: Python
